CHANGELOG
LICENSE
MANIFEST.in
README.rst
requirements.txt
setup.cfg
setup.py
sbpipe/VERSION
sbpipe/__init__.py
sbpipe/__main__.py
sbpipe/is_package_installed.r
sbpipe/logging_config.ini
sbpipe/sbpipe_cleanup.py
sbpipe/sbpipe_move_datasets.py
sbpipe.egg-info/PKG-INFO
sbpipe.egg-info/SOURCES.txt
sbpipe.egg-info/dependency_links.txt
sbpipe.egg-info/entry_points.txt
sbpipe.egg-info/not-zip-safe
sbpipe.egg-info/requires.txt
sbpipe.egg-info/top_level.txt
sbpipe/pl/__init__.py
sbpipe/pl/pipeline.py
sbpipe/pl/create/__init__.py
sbpipe/pl/create/newproj.py
sbpipe/pl/pe/__init__.py
sbpipe/pl/pe/parest.py
sbpipe/pl/ps1/__init__.py
sbpipe/pl/ps1/parscan1.py
sbpipe/pl/ps2/__init__.py
sbpipe/pl/ps2/parscan2.py
sbpipe/pl/sim/__init__.py
sbpipe/pl/sim/sim.py
sbpipe/report/__init__.py
sbpipe/report/latex_reports.py
sbpipe/simul/__init__.py
sbpipe/simul/pl_simul.py
sbpipe/simul/simul.py
sbpipe/simul/copasi/__init__.py
sbpipe/simul/copasi/copasi.py
sbpipe/simul/copasi/model_checking.py
sbpipe/simul/python/__init__.py
sbpipe/simul/python/python.py
sbpipe/snakemake/__init__.py
sbpipe/snakemake/data_generation.py
sbpipe/snakemake/model_checking.py
sbpipe/snakemake/pe_analysis.py
sbpipe/snakemake/pe_collection.py
sbpipe/snakemake/pe_postproc.py
sbpipe/snakemake/preproc.py
sbpipe/snakemake/ps1_analysis.py
sbpipe/snakemake/ps1_postproc.py
sbpipe/snakemake/ps2_analysis.py
sbpipe/snakemake/ps2_postproc.py
sbpipe/snakemake/sim_analysis.py
sbpipe/snakemake/sim_postproc.py
sbpipe/utils/__init__.py
sbpipe/utils/dependencies.py
sbpipe/utils/io.py
sbpipe/utils/parcomp.py
sbpipe/utils/rand.py
sbpipe/utils/re_utils.py