Metadata-Version: 1.1
Name: sbpipe
Version: 4.20.0
Summary: Pipelines for systems modelling of biological networks.
Home-page: http://sbpipe.readthedocs.io
Author: Piero Dalle Pezze
Author-email: piero.dallepezze@gmail.com
License: MIT
Download-URL: https://github.com/pdp10/sbpipe
Keywords: simulation,parameter-estimation,modelling,pipeline
Platform: UNKNOWN
Classifier: Development Status :: 5 - Production/Stable
Classifier: Environment :: Console
Classifier: Intended Audience :: Science/Research
Classifier: License :: OSI Approved :: MIT License
Classifier: Natural Language :: English
Classifier: Programming Language :: Python :: 2
Classifier: Programming Language :: Python :: 3
Classifier: Operating System :: OS Independent
Classifier: Topic :: Scientific/Engineering :: Bio-Informatics
Classifier: Topic :: Scientific/Engineering :: Medical Science Apps.
